LICENSE
MANIFEST.in
bootstrap.py
buildout.cfg
setup.cfg
setup.py
examples/short_test.po
src/README.txt
src/TODO.txt
src/ikazuchi/__init__.py
src/ikazuchi.plugins.pofile.egg-info/PKG-INFO
src/ikazuchi.plugins.pofile.egg-info/SOURCES.txt
src/ikazuchi.plugins.pofile.egg-info/dependency_links.txt
src/ikazuchi.plugins.pofile.egg-info/entry_points.txt
src/ikazuchi.plugins.pofile.egg-info/namespace_packages.txt
src/ikazuchi.plugins.pofile.egg-info/requires.txt
src/ikazuchi.plugins.pofile.egg-info/top_level.txt
src/ikazuchi/plugins/__init__.py
src/ikazuchi/plugins/pofile.py
src/ikazuchi/tests/test_pep8.py
src/ikazuchi/tests/test_pofile_handler.py
src/ikazuchi/tests/data/__init__.py
src/ikazuchi/tests/data/po/__init__.py
src/ikazuchi/tests/data/po/markup_notranslate.py